{
  "qa_pairs": [
    {
        "id": "saud-hello-001",
  "category": "saudação",
  "questions": [
    "oi", "olá", "ola", "bom dia", "boa tarde", "boa noite",
    "e aí", "alô", "alo", "tudo bem?", "como vai?", "hey"
  ],
  "answer": "Olá! 👋 Eu sou o assistente virtual da <b>Tecnoagil</b>. Como posso te ajudar hoje?<br><br>Aqui estão algumas perguntas que você pode fazer para começar:<br>🔹 O que é a Tecnoagil?<br>🔹 Quais serviços vocês oferecem?<br>🔹 Como posso entrar em contato?<br>🔹 Qual é o horário de atendimento?<br>🔹 Vocês oferecem suporte técnico?<br>🔹 Onde a empresa está localizada?<br>🔹 Quais formas de pagamento vocês aceitam?<br>🔹 Quanto tempo leva a instalação?"
},

    {
      "id": "inst-quem-somos-001",
      "category": "institucional",
      "questions": [
        "o que é a Tecnoagil?",
        "quem é a Tecnoagil?",
        "me fale sobre a empresa Tecnoagil",
        "você pode me explicar o que é a Tecnoagil?",
        "sobre a Tecnoagil",
        "o que vocês são?",
        "qual é a área de atuação da Tecnoagil?"
      ],
      "answer": "A <b>Tecnoagil</b> é uma empresa especializada em <b>soluções tecnológicas e segurança</b>, atuando com <b>monitoramento</b>, <b>câmeras</b>, <b>controle de acesso</b>, <b>redes corporativas</b> e <b>suporte técnico</b>. Nosso foco é entregar projetos <b>confiáveis</b> e <b>sob medida</b> para cada necessidade."
    },

    {
      "id": "contato-canais-001",
      "category": "vendas",
      "questions": [
        "como posso entrar em contato?",
        "quero falar com vocês, como faço?",
        "formas de contato com a Tecnoagil?",
        "como falo com um atendente?",
        "telefone da Tecnoagil",
        "whatsapp da Tecnoagil",
        "email de contato"
      ],
      "answer": "Se preferir falar diretamente com a nossa equipe, todas as opções de contato estão disponíveis na aba <b>Contato</b> aqui mesmo no site, onde você poderá acessar nosso WhatsApp, telefone e formulário de atendimento de forma rápida e prática" 
       },

    {
      "id": "suporte-horario-001",
      "category": "atendimento",
      "questions": [
        "qual é o horário de atendimento?",
        "quando vocês atendem?",
        "horários de funcionamento da Tecnoagil?",
        "atendimento de vocês qual horário?",
        "funcionamento",
        "que horas vocês abrem?"
      ],
      "answer": "Nosso <b>atendimento comercial</b> é de <b>segunda a sexta</b>, das <b>08:00 às 18:00</b>. <br>Para <b>suporte emergencial</b>, clientes com contrato possuem canal prioritário 24h."
    },

    {
      "id": "suporte-pos-venda-001",
      "category": "suporte",
      "questions": [
        "vocês têm suporte?",
        "como funciona o suporte pós-venda?",
        "a Tecnoagil oferece suporte técnico?",
        "tem atendimento depois da instalação?",
        "suporte técnico",
        "manutenção preventiva"
      ],
      "answer": "Sim! Oferecemos <b>suporte técnico</b> e <b>planos de manutenção preventiva</b> para clientes contratados. <br>Planos incluem: <ul><li>Atendimento remoto e presencial</li><li>Atualizações e inspeções periódicas</li><li>Canal de <b>suporte 24h</b> para incidentes críticos</li></ul>"
    },

    {
      "id": "local-endereco-001",
      "category": "institucional",
      "questions": [
        "onde vocês ficam localizados?",
        "qual o endereço da Tecnoagil?",
        "onde é a sede de vocês?",
        "endereço da Tecnoagil?",
        "localização",
        "vocês atendem minha cidade?"
      ],
      "answer": "Nossa sede fica em <b>Vitória da Conquista – BA</b>. Atendemos toda a região e também realizamos serviços sob demanda em outras localidades. <br>Fale no WhatsApp para confirmar disponibilidade na sua cidade."
    },

    {
      "id": "serv-prazo-instalacao-001",
      "category": "serviços",
      "questions": [
        "quanto tempo leva a instalação de câmeras?",
        "prazo de instalação de sistema?",
        "em quanto tempo instalam?",
        "qual o prazo para concluir o serviço?",
        "tempo de implantação",
        "prazo de projeto"
      ],
      "answer": "A instalação costuma levar de <b>2 a 5 dias úteis</b>, variando conforme <b>tamanho</b>, <b>complexidade</b> e <b>infraestrutura</b> do local. Projetos maiores podem demandar um cronograma específico."
    },

    {
      "id": "vendas-pagamento-001",
      "category": "pagamento",
      "questions": [
        "quais formas de pagamento vocês aceitam?",
        "como posso pagar?",
        "aceitam boleto ou cartão?",
        "me diga os métodos de pagamento",
        "formas de pagamento",
        "posso pagar no pix?"
      ],
      "answer": "Aceitamos <b>cartão de crédito</b>, <b>boleto bancário</b> e <b>PIX</b>. Em projetos maiores, podemos avaliar <b>condições diferenciadas</b>."
    },

    {
      "id": "vendas-orcamento-001",
      "category": "vendas",
      "questions": [
        "quero um orçamento",
        "como faço um orçamento?",
        "quanto custa?",
        "pode enviar uma proposta?",
        "como solicitar proposta?",
        "orçamento de instalação"
      ],
      "answer": "Para um orçamento assertivo, precisamos de algumas informações: <ul><li>Quantidade de câmeras/pontos</li><li>Planta ou medidas do local</li><li>Tipo de acesso (biometria, cartão, etc.)</li><li>Prazo desejado</li></ul> Envie pelo <b>WhatsApp</b> ou <b>e-mail</b> e retornamos com a proposta."
    },

    {
      "id": "serv-visita-tecnica-001",
      "category": "serviços",
      "questions": [
        "vocês fazem visita técnica?",
        "como agendar uma visita?",
        "pode fazer um diagnóstico no local?",
        "vistorias e levantamento"
      ],
      "answer": "Sim. Realizamos <b>visita técnica</b> para levantamento de requisitos, medição e testes. Agende pelo WhatsApp informando <b>endereço</b> e <b>disponibilidade</b>."
    },
{
  "id": "serv-lista-001",
  "category": "serviços",
  "questions": [
    "quais serviços vocês oferecem?",
    "lista de serviços",
    "me fale sobre os serviços",
    "o que vocês fazem?",
    "quais soluções a Tecnoagil disponibiliza?",
    "mostre todos os serviços"
  ],
  "answer": "Aqui estão os principais serviços que a <b>Tecnoagil</b> oferece:<br><br>🔹 Portaria Remota<br>🔹 Monitoramento 24h<br>🔹 Controle de Acesso<br>🔹 Rastreamento Veicular<br>🔹 Vídeo-monitoramento<br>🔹 Automação Residencial/Predial<br>🔹 Terceirização de Mão de Obra<br>🔹 Sistemas de Incêndio<br>🔹 Rede Estruturada<br>🔹 Telefonia IP<br>🔹 Energia Solar<br><br><i>Você pode perguntar sobre qualquer um deles para saber mais detalhes.</i>"
}
,
    {
      "id": "comp-lgpd-001",
      "category": "institucional",
      "questions": [
        "vocês seguem a LGPD?",
        "conformidade com lgpd",
        "privacidade de dados",
        "como tratam meus dados?"
      ],
      "answer": "Seguimos princípios da <b>LGPD</b>, aplicando <b>mínimo necessário</b>, <b>finalidade</b> e <b>segurança</b> no tratamento de dados. Para detalhes, solicite nossa <b>Política de Privacidade</b>."
    },

    {
      "id": "suporte-sla-001",
      "category": "suporte",
      "questions": [
        "qual o SLA de atendimento?",
        "tempo de resposta do suporte",
        "quanto tempo para atender um chamado?",
        "sla de suporte"
      ],
      "answer": "Para contratos com SLA: <ul><li><b>Críticos</b>: resposta em até <b>2h</b> (24x7)</li><li><b>Alta</b>: até <b>4h</b> úteis</li><li><b>Média/Baixa</b>: até <b>8–24h</b> úteis</li></ul> SLA pode variar conforme o plano contratado."
    },

       
    {
      "id": "serv-portaria-remota-001",
      "category": "serviços",
      "questions": [
        "portaria remota",
        "vocês fazem portaria remota?",
        "como funciona a portaria remota?",
        "portaria à distância",
        "reduzir custos com portaria",
        "portaria para condomínio"
      ],
      "answer": "<b>Portaria Remota</b><br/>Controle de acesso à distância com monitoramento em tempo real, reduzindo custos e elevando a segurança de condomínios e empresas."
    },
    {
      "id": "serv-monitoramento-24h-001",
      "category": "serviços",
      "questions": [
        "monitoramento 24h",
        "vocês monitoram 24 horas?",
        "central de monitoramento",
        "monitoramento de alarmes",
        "monitoramento em tempo real"
      ],
      "answer": "<b>Monitoramento 24h</b><br/>Central equipada e equipe especializada para atuar de forma preventiva e reativa, garantindo tranquilidade todos os dias."
    },
    {
      "id": "serv-controle-acesso-001",
      "category": "serviços",
      "questions": [
        "controle de acesso",
        "vocês implantam controle de acesso?",
        "biometria e catraca",
        "cartão de proximidade",
        "qr code ou reconhecimento facial"
      ],
      "answer": "<b>Controle de Acesso</b><br/>Gestão segura de entrada e saída com cartões, biometria, QR Code e reconhecimento facial, com relatórios e integração a câmeras."
    },
    {
      "id": "serv-rastreamento-veicular-001",
      "category": "serviços",
      "questions": [
        "rastreamento veicular",
        "vocês rastreiam veículos?",
        "gps para frota",
        "monitorar veículos em tempo real",
        "alerta de velocidade"
      ],
      "answer": "<b>Rastreamento Veicular</b><br/>Localização em tempo real, histórico de rotas, alertas de desvios e relatórios de gestão de frotas para reduzir custos e aumentar a segurança."
    },
    {
      "id": "serv-video-monitoramento-001",
      "category": "serviços",
      "questions": [
        "vídeo-monitoramento",
        "câmeras de segurança",
        "acompanhar câmeras pelo celular",
        "gravação em nuvem",
        "visão noturna"
      ],
      "answer": "<b>Vídeo-monitoramento</b><br/>Câmeras HD com visão noturna, gravação em nuvem e integração com alarmes e controle de acesso."
    },
    {
      "id": "serv-automacao-001",
      "category": "serviços",
      "questions": [
        "automação residencial",
        "automação predial",
        "casa inteligente",
        "controlar iluminação e climatização"
      ],
      "answer": "<b>Automação Residencial/Predial</b><br/>Controle centralizado de iluminação, climatização, câmeras, alarmes e portões. Mais conforto, segurança e eficiência energética."
    },
    {
      "id": "serv-terceirizacao-001",
      "category": "serviços",
      "questions": [
        "terceirização de mão de obra",
        "terceirização de portaria",
        "serviços terceirizados",
        "limpeza terceirizada",
        "vigia e recepção"
      ],
      "answer": "<b>Terceirização de Mão de Obra</b><br/>Profissionais qualificados para portaria, vigilância, recepção, limpeza e manutenção. Qualidade e redução de custos trabalhistas."
    },
    {
      "id": "serv-incendio-001",
      "category": "serviços",
      "questions": [
        "sistemas de incêndio",
        "alarme de incêndio",
        "detector de fumaça",
        "sprinklers"
      ],
      "answer": "<b>Sistemas de Incêndio</b><br/>Projetos personalizados com detectores, alarmes, sprinklers e integração com monitoramento 24h."
    },
    {
      "id": "serv-rede-estruturada-001",
      "category": "serviços",
      "questions": [
        "rede estruturada",
        "cabeamento estruturado",
        "organização de racks",
        "rede corporativa"
      ],
      "answer": "<b>Rede Estruturada</b><br/>Cabeamento de alta performance, organização de racks e switches gerenciáveis. Escalabilidade e segurança para sua empresa."
    },
    {
      "id": "serv-telefonia-ip-001",
      "category": "serviços",
      "questions": [
        "telefonia ip",
        "ramal voip",
        "pabx ip",
        "chamadas pela internet"
      ],
      "answer": "<b>Telefonia IP</b><br/>Comunicação corporativa via internet: voz, vídeo e dados, redução de custos, ramais virtuais e gravação de chamadas."
    },
    {
      "id": "serv-energia-solar-001",
      "category": "serviços",
      "questions": [
        "energia solar",
        "painéis solares",
        "fotovoltaico",
        "instalação de energia solar",
        "economia na conta de luz"
      ],
      "answer": "<b>Energia Solar</b><br/>Projetos fotovoltaicos completos: viabilidade, instalação de módulos/inversores e monitoramento de geração."
    }
  ]
}
